[
  {
    "FirstName": "Carlos",
    "LastName": "Anderson",
    "Age": 78,
    "Id": 22
  },
  {
    "FirstName": "Dewey",
    "LastName": "Anderson",
    "Age": 81,
    "Id": 16
  },
  {
    "FirstName": "Leia",
    "LastName": "Anderson",
    "Age": 72,
    "Id": 13
  },
  {
    "FirstName": "Lukas",
    "LastName": "Anderson",
    "Age": 59,
    "Id": 14
  },
  {
    "FirstName": "Sadie",
    "LastName": "Anderson",
    "Age": 18,
    "Id": 11
  },
  {
    "FirstName": "Tomas",
    "LastName": "Chan",
    "Age": 48,
    "Id": 31
  },
  {
    "FirstName": "Carlos",
    "LastName": "Drew",
    "Age": 72,
    "Id": 15
  },
  {
    "FirstName": "Jose",
    "LastName": "Harrison",
    "Age": 69,
    "Id": 7
  },
  {
    "FirstName": "Leia",
    "LastName": "Harrison",
    "Age": 70,
    "Id": 27
  },
  {
    "FirstName": "Carlos",
    "LastName": "Larsen",
    "Age": 56,
    "Id": 2
  },
  {
    "FirstName": "Joel",
    "LastName": "Larsen",
    "Age": 56,
    "Id": 21
  },
  {
    "FirstName": "Leia",
    "LastName": "Larsen",
    "Age": 33,
    "Id": 30
  },
  {
    "FirstName": "Sadie",
    "LastName": "Larsen",
    "Age": 20,
    "Id": 4
  },
  {
    "FirstName": "Tomas",
    "LastName": "Larsen",
    "Age": 45,
    "Id": 5
  },
  {
    "FirstName": "Lukas",
    "LastName": "Liberty",
    "Age": 67,
    "Id": 19
  },
  {
    "FirstName": "Sara",
    "LastName": "Liberty",
    "Age": 79,
    "Id": 3
  },
  {
    "FirstName": "Tomas",
    "LastName": "Powell",
    "Age": 25,
    "Id": 26
  },
  {
    "FirstName": "Joel",
    "LastName": "Ray",
    "Age": 40,
    "Id": 12
  },
  {
    "FirstName": "Carlos",
    "LastName": "Ronan",
    "Age": 59,
    "Id": 17
  },
  {
    "FirstName": "Dewey",
    "LastName": "Ronan",
    "Age": 50,
    "Id": 23
  },
  {
    "FirstName": "Jose",
    "LastName": "Ronan",
    "Age": 28,
    "Id": 20
  },
  {
    "FirstName": "Leia",
    "LastName": "Ronan",
    "Age": 24,
    "Id": 6
  },
  {
    "FirstName": "Sadie",
    "LastName": "Ronan",
    "Age": 34,
    "Id": 18
  },
  {
    "FirstName": "Tomas",
    "LastName": "Ronan",
    "Age": 33,
    "Id": 9
  }
]